<?xml version="1.0" encoding="UTF-8"?>
<!DOCTYPE mapper PUBLIC "-//mybatis.org//DTD Mapper 3.0//EN" "http://mybatis.org/dtd/mybatis-3-mapper.dtd">
<mapper namespace="com.djsenglish.dao.ConcernMapper">
  <resultMap id="BaseResultMap" type="com.djsenglish.pojo.Concern">
    <constructor>
      <idArg column="id" javaType="java.lang.Integer" jdbcType="INTEGER" />
      <arg column="user" javaType="java.lang.Integer" jdbcType="INTEGER" />
      <arg column="friending" javaType="java.lang.Integer" jdbcType="INTEGER" />
      <arg column="update_time" javaType="java.util.Date" jdbcType="TIMESTAMP" />
      <arg column="create_time" javaType="java.util.Date" jdbcType="TIMESTAMP" />
    </constructor>
  </resultMap>
  <sql id="Base_Column_List">
    id, user, friending, update_time, create_time
  </sql>
  <select id="selectByPrimaryKey" parameterType="java.lang.Integer" resultMap="BaseResultMap">
    select 
    <include refid="Base_Column_List" />
    from concern
    where id = #{id,jdbcType=INTEGER}
  </select>
  <delete id="deleteByPrimaryKey" parameterType="java.lang.Integer">
    delete from concern
    where id = #{id,jdbcType=INTEGER}
  </delete>
  <insert id="insert" parameterType="com.djsenglish.pojo.Concern">
    insert into concern (id, user, friending, 
      update_time, create_time)
    values (#{id,jdbcType=INTEGER}, #{user,jdbcType=INTEGER}, #{friending,jdbcType=INTEGER}, 
      #{updateTime,jdbcType=TIMESTAMP}, #{createTime,jdbcType=TIMESTAMP})
  </insert>
  <insert id="insertSelective" parameterType="com.djsenglish.pojo.Concern">
    insert into concern
    <trim prefix="(" suffix=")" suffixOverrides=",">
      <if test="id != null">
        id,
      </if>
      <if test="user != null">
        user,
      </if>
      <if test="friending != null">
        friending,
      </if>
      <if test="updateTime != null">
        update_time,
      </if>
      <if test="createTime != null">
        create_time,
      </if>
    </trim>
    <trim prefix="values (" suffix=")" suffixOverrides=",">
      <if test="id != null">
        #{id,jdbcType=INTEGER},
      </if>
      <if test="user != null">
        #{user,jdbcType=INTEGER},
      </if>
      <if test="friending != null">
        #{friending,jdbcType=INTEGER},
      </if>
      <if test="updateTime != null">
        #{updateTime,jdbcType=TIMESTAMP},
      </if>
      <if test="createTime != null">
        #{createTime,jdbcType=TIMESTAMP},
      </if>
    </trim>
  </insert>
  <update id="updateByPrimaryKeySelective" parameterType="com.djsenglish.pojo.Concern">
    update concern
    <set>
      <if test="user != null">
        user = #{user,jdbcType=INTEGER},
      </if>
      <if test="friending != null">
        friending = #{friending,jdbcType=INTEGER},
      </if>
      <if test="updateTime != null">
        update_time = #{updateTime,jdbcType=TIMESTAMP},
      </if>
      <if test="createTime != null">
        create_time = #{createTime,jdbcType=TIMESTAMP},
      </if>
    </set>
    where id = #{id,jdbcType=INTEGER}
  </update>
  <update id="updateByPrimaryKey" parameterType="com.djsenglish.pojo.Concern">
    update concern
    set user = #{user,jdbcType=INTEGER},
      friending = #{friending,jdbcType=INTEGER},
      update_time = #{updateTime,jdbcType=TIMESTAMP},
      create_time = #{createTime,jdbcType=TIMESTAMP}
    where id = #{id,jdbcType=INTEGER}
  </update>
  <resultMap id="BaseResultMap" type="com.djsenglish.pojo.Concern">
    <constructor>
      <idArg column="id" javaType="java.lang.Integer" jdbcType="INTEGER" />
      <arg column="user" javaType="java.lang.Integer" jdbcType="INTEGER" />
      <arg column="friending" javaType="java.lang.Integer" jdbcType="INTEGER" />
      <arg column="update_time" javaType="java.util.Date" jdbcType="TIMESTAMP" />
      <arg column="create_time" javaType="java.util.Date" jdbcType="TIMESTAMP" />
    </constructor>
  </resultMap>
  <sql id="Base_Column_List">
    id, user, friending, update_time, create_time
  </sql>
  <select id="selectByPrimaryKey" parameterType="java.lang.Integer" resultMap="BaseResultMap">
    select
    <include refid="Base_Column_List" />
    from concern
    where id = #{id,jdbcType=INTEGER}
  </select>
  <select id="selectCount" parameterType="map" resultType="java.lang.Integer">
    select count(*) from concern
    where user = #{userId}
    and friending = #{friendId}
  </select>
  <select id="selectByUserId" parameterType="int" resultType="int">
    select
    friending
    from concern
    where user = #{userId}
  </select>
  <delete id="deleteByPrimaryKey" parameterType="java.lang.Integer">
    delete from concern
    where id = #{id,jdbcType=INTEGER}
  </delete>
  <delete id="deleteConcern" parameterType="map">
    delete from concern
    where user = #{userId}
    and friending = #{friendId}
  </delete>
  <insert id="insert" parameterType="com.djsenglish.pojo.Concern">
    insert into concern (id, user, friending,
      update_time, create_time)
    values (#{id,jdbcType=INTEGER}, #{user,jdbcType=INTEGER}, #{friending,jdbcType=INTEGER},
      now(), now())
  </insert>
  <insert id="insertSelective" parameterType="com.djsenglish.pojo.Concern">
    insert into concern
    <trim prefix="(" suffix=")" suffixOverrides=",">
      <if test="id != null">
        id,
      </if>
      <if test="user != null">
        user,
      </if>
      <if test="friending != null">
        friending,
      </if>
        update_time,
        create_time,
    </trim>
    <trim prefix="values (" suffix=")" suffixOverrides=",">
      <if test="id != null">
        #{id,jdbcType=INTEGER},
      </if>
      <if test="user != null">
        #{user,jdbcType=INTEGER},
      </if>
      <if test="friending != null">
        #{friending,jdbcType=INTEGER},
      </if>
        now(),
        now(),
    </trim>
  </insert>
  <update id="updateByPrimaryKeySelective" parameterType="com.djsenglish.pojo.Concern">
    update concern
    <set>
      <if test="user != null">
        user = #{user,jdbcType=INTEGER},
      </if>
      <if test="friending != null">
        friending = #{friending,jdbcType=INTEGER},
      </if>
      <if test="updateTime != null">
        update_time = now(),
      </if>
      <if test="createTime != null">
        create_time = #{createTime,jdbcType=TIMESTAMP},
      </if>
    </set>
    where id = #{id,jdbcType=INTEGER}
  </update>
  <update id="updateByPrimaryKey" parameterType="com.djsenglish.pojo.Concern">
    update concern
    set user = #{user,jdbcType=INTEGER},
      friending = #{friending,jdbcType=INTEGER},
      update_time = #{updateTime,jdbcType=TIMESTAMP},
      create_time = #{createTime,jdbcType=TIMESTAMP}
    where id = #{id,jdbcType=INTEGER}
  </update>
</mapper>